streetfighter/__init__.py
streetfighter/common.py
streetfighter/streetfighter.py
streetfighter-0.0.1.dist-info/LICENSE
streetfighter-0.0.1.dist-info/METADATA
streetfighter-0.0.1.dist-info/WHEEL
streetfighter-0.0.1.dist-info/entry_points.txt
streetfighter-0.0.1.dist-info/top_level.txt
streetfighter-0.0.1.dist-info/RECORD
